LICENSE
README.md
setup.py
Primice/__init__.py
Primice.egg-info/PKG-INFO
Primice.egg-info/SOURCES.txt
Primice.egg-info/dependency_links.txt
Primice.egg-info/requires.txt
Primice.egg-info/top_level.txt
Primice/Mongo/__init__.py
Primice/Mongo/to_Mongodb.py
Primice/MySQL/DataTable.py
Primice/MySQL/__init__.py
Primice/MySQL/to_MySQL.py
Primice/Proxy/Proxy.py
Primice/Proxy/__init__.py
Primice/Spider/Log.py
Primice/Spider/Twitter爬虫.py
Primice/Spider/__init__.py
Primice/Spider/http_raw2requests.py
Primice/Utils/BloomFilter.py
Primice/Utils/__init__.py
Primice/Utils/chaojiying.py