Metadata-Version: 2.1
Name: Primice
Version: 1.1.1
Summary: A Multifunctional library for personal use
Home-page: 
Author: Primice
Author-email: 1121796946@qq.com
Classifier: Programming Language :: Python :: 3
Classifier: License :: OSI Approved :: MIT License
Classifier: Operating System :: OS Independent
License-File: LICENSE
